{
    "topic": "animals-easy-and-simple",
    "generatedAt": "2026-03-09T13:30:28.635Z",
    "questions": [
        {
            "id": 21,
            "text": "What is the primary source of food for giant pandas?",
            "options": [
                {
                    "id": "A",
                    "text": "Insects and small reptiles"
                },
                {
                    "id": "B",
                    "text": "Fruits and berries"
                },
                {
                    "id": "C",
                    "text": "Grasses and small mammals"
                },
                {
                    "id": "D",
                    "text": "Bamboo shoots and leaves"
                }
            ],
            "correct": "D",
            "category": "animals-easy-and-simple"
        },
        {
            "id": 22,
            "text": "Which species of bird is known for its distinctive call that sounds like laughter?",
            "options": [
                {
                    "id": "A",
                    "text": "Penguin"
                },
                {
                    "id": "B",
                    "text": "Pelican"
                },
                {
                    "id": "C",
                    "text": "Kookaburra"
                },
                {
                    "id": "D",
                    "text": "Parrot"
                }
            ],
            "correct": "C",
            "category": "animals-easy-and-simple"
        },
        {
            "id": 23,
            "text": "What is the fastest land animal?",
            "options": [
                {
                    "id": "A",
                    "text": "Cheetah"
                },
                {
                    "id": "B",
                    "text": "Leopard"
                },
                {
                    "id": "C",
                    "text": "Giraffe"
                },
                {
                    "id": "D",
                    "text": "Lion"
                }
            ],
            "correct": "A",
            "category": "animals-easy-and-simple"
        },
        {
            "id": 24,
            "text": "Which animal has the longest migration route?",
            "options": [
                {
                    "id": "A",
                    "text": "Caribou"
                },
                {
                    "id": "B",
                    "text": "Gray whale"
                },
                {
                    "id": "C",
                    "text": "Monarch butterfly"
                },
                {
                    "id": "D",
                    "text": "Arctic tern"
                }
            ],
            "correct": "D",
            "category": "animals-easy-and-simple"
        },
        {
            "id": 25,
            "text": "What is the largest species of shark?",
            "options": [
                {
                    "id": "A",
                    "text": "Great white shark"
                },
                {
                    "id": "B",
                    "text": "Tiger shark"
                },
                {
                    "id": "C",
                    "text": "Hammerhead shark"
                },
                {
                    "id": "D",
                    "text": "Whale shark"
                }
            ],
            "correct": "D",
            "category": "animals-easy-and-simple"
        },
        {
            "id": 26,
            "text": "Which animal has the strongest bite force?",
            "options": [
                {
                    "id": "A",
                    "text": "Saltwater crocodile"
                },
                {
                    "id": "B",
                    "text": "Great white shark"
                },
                {
                    "id": "C",
                    "text": "Black mamba"
                },
                {
                    "id": "D",
                    "text": "Lion"
                }
            ],
            "correct": "A",
            "category": "animals-easy-and-simple"
        },
        {
            "id": 27,
            "text": "What is the smallest species of mammal?",
            "options": [
                {
                    "id": "A",
                    "text": "Mouse"
                },
                {
                    "id": "B",
                    "text": "Squirrel"
                },
                {
                    "id": "C",
                    "text": "Rabbit"
                },
                {
                    "id": "D",
                    "text": "Bumblebee bat"
                }
            ],
            "correct": "D",
            "category": "animals-easy-and-simple"
        },
        {
            "id": 28,
            "text": "Which animal is known for its unique ability to change its body color?",
            "options": [
                {
                    "id": "A",
                    "text": "Chameleon"
                },
                {
                    "id": "B",
                    "text": "Cuttlefish"
                },
                {
                    "id": "C",
                    "text": "Squid"
                },
                {
                    "id": "D",
                    "text": "Octopus"
                }
            ],
            "correct": "A",
            "category": "animals-easy-and-simple"
        },
        {
            "id": 29,
            "text": "What is the largest species of turtle?",
            "options": [
                {
                    "id": "A",
                    "text": "Aldabra tortoise"
                },
                {
                    "id": "B",
                    "text": "Leatherback sea turtle"
                },
                {
                    "id": "C",
                    "text": "Green sea turtle"
                },
                {
                    "id": "D",
                    "text": "Loggerhead sea turtle"
                }
            ],
            "correct": "B",
            "category": "animals-easy-and-simple"
        },
        {
            "id": 30,
            "text": "Which animal has the longest lifespan?",
            "options": [
                {
                    "id": "A",
                    "text": "Whale"
                },
                {
                    "id": "B",
                    "text": "Ocean quahog"
                },
                {
                    "id": "C",
                    "text": "Tortoise"
                },
                {
                    "id": "D",
                    "text": "Elephant"
                }
            ],
            "correct": "B",
            "category": "animals-easy-and-simple"
        }
    ]
}